tgback_x/__init__.py
tgback_x/crypto.py
tgback_x/defaults.py
tgback_x/errors.py
tgback_x/protocols.py
tgback_x/providers.py
tgback_x/tools.py
tgback_x/version.py
tgback_x-1.0.dist-info/LICENSE
tgback_x-1.0.dist-info/METADATA
tgback_x-1.0.dist-info/WHEEL
tgback_x-1.0.dist-info/top_level.txt
tgback_x-1.0.dist-info/RECORD
