Metadata-Version: 2.1
Name: tgback-x
Version: 1.0
Summary: tgback-x — a library for making Telegram account backups
Home-page: https://github.com/NonProjects/tgback-x
Download-URL: https://github.com/NonProjects/tgback-x/archive/refs/tags/v1.0.tar.gz
Author-email: thenonproton@pm.me
License: MIT
Keywords: Telegram,Backup,Account,Non-official
License-File: LICENSE
Requires-Dist: pyaes==1.6.1
Requires-Dist: telethon==1.38.1
Requires-Dist: phrasegen==1.0.0
